packageTest/__init__.py
packageTest/__main__.py
packageTest/apis.py
packageTest/func.py
Criminal_IP_Test-1.0.2.dist-info/METADATA
Criminal_IP_Test-1.0.2.dist-info/WHEEL
Criminal_IP_Test-1.0.2.dist-info/top_level.txt
Criminal_IP_Test-1.0.2.dist-info/RECORD
