Metadata-Version: 2.1
Name: Criminal-IP-Test
Version: 1.0.2
Summary: Criminal IP Package Test
Home-page: https://www.criminalip.io/ko
Author: tygo
Author-email: tygo@aispera.com
License: UNKNOWN
Platform: UNKNOWN
Requires-Dist: requests
Requires-Dist: click
